{
  "version": 1,
  "id": "demo-pipeline",
  "name": "Demo",
  "telemetry": {
    "log_events": ["flow_event"],
    "queue_prefixes": ["intake-queue", "publish-queue"],
    "function_prefixes": [],
    "worker_prefixes": ["intake-worker", "publish-worker"],
    "step_prefixes": [
      "external-event",
      "intake-worker.",
      "normalize-record",
      "input-valid",
      "publish-worker."
    ],
    "span_prefixes": [],
    "span_names": []
  },
  "keep_context": {
    "parent_spans": true,
    "root_spans": true,
    "error_events": true,
    "unmapped_events_for_kept_traces": true
  }
}
